pyxu_ldct_reader/__init__.py
pyxu_ldct_reader/dicom_utils.py
pyxu_ldct_reader/geometry_utils.py
pyxu_ldct_reader/mayo_dicom_dict.py
pyxu_ldct_reader/reader.py
pyxu_ldct_reader-1.0.0.dist-info/METADATA
pyxu_ldct_reader-1.0.0.dist-info/WHEEL
pyxu_ldct_reader-1.0.0.dist-info/licenses/LICENSE
pyxu_ldct_reader-1.0.0.dist-info/RECORD
