Metadata-Version: 2.3
Name: pyxu_ldct_reader
Version: 1.0.0
Summary: Data loader that reads and parses clinical CT sinograms in the LDCT-and-Projection-data repository and map them to Pyxu's XRayTransform
Project-URL: download, https://github.com/EPFL-Center-for-Imaging/pyxu-ldct-reader
Author-email: Joan Rue Queralt <joan.rue.q@gmail.com>
License-Expression: MIT
License-File: LICENSE
Classifier: Development Status :: 4 - Beta
Classifier: Framework :: Pycsou
Classifier: Intended Audience :: Science/Research
Classifier: License :: OSI Approved :: MIT License
Classifier: Programming Language :: Python :: 3.10
Classifier: Programming Language :: Python :: 3.11
Classifier: Programming Language :: Python :: 3.12
Classifier: Programming Language :: Python :: Implementation :: CPython
Classifier: Topic :: Scientific/Engineering
Requires-Python: <3.13,>=3.10
Requires-Dist: pydicom
Requires-Dist: pyxu
Provides-Extra: dev
Requires-Dist: pyxu[dev]; extra == 'dev'
